{"type":"result","subtype":"success","is_error":false,"duration_ms":111570,"duration_api_ms":133043,"num_turns":4,"result":"I've completed the strict review of the changes. Here's my analysis in JSON format:\n\n```json\n{\n  \"summary\": \"Addition of PowerShell scripts for Windows support and minor documentation updates. The changes introduce platform-specific tooling but have several critical issues: missing error handling, test content in production docs, validation gaps, no tests, and incomplete PowerShell migration.\",\n  \"risks\": [\n    {\n      \"severity\": \"HIGH\",\n      \"location\": \"README.md:52\",\n      \"description\": \"Test/debug line added to production documentation: 'This is a test line for the dry run.' This should not be committed to main branch.\",\n      \"impact\": \"Unprofessional appearance, suggests incomplete testing or accidental commit.\"\n    },\n    {\n      \"severity\": \"HIGH\",\n      \"location\": \"scripts/miyabi-finish.ps1:11\",\n      \"description\": \"Unconditional git push without validation of working directory state, uncommitted changes, or push success. No error handling if push fails.\",\n      \"impact\": \"Could push broken/incomplete code, or continue to PR creation even if push fails, creating inconsistent state.\"\n    },\n    {\n      \"severity\": \"HIGH\",\n      \"location\": \"scripts/miyabi-finish.ps1:2-8\",\n      \"description\": \"Issue parameter is not mandatory and has no validation. User can execute script with empty/invalid issue number.\",\n      \"impact\": \"PR creation will fail or create PR with malformed title/references.\"\n    },\n    {\n      \"severity\": \"MEDIUM\",\n      \"location\": \"scripts/miyabi-finish.ps1:21\",\n      \"description\": \"PR creation uses --body-file but doesn't validate file exists or handle creation failures. No error checking after gh pr create.\",\n      \"impact\": \"Silent failures possible. User gets success message even if PR creation failed.\"\n    },\n    {\n      \"severity\": \"MEDIUM\",\n      \"location\": \"scripts/ai/pr_review.ps1:19-21\",\n      \"description\": \"Backtick line continuation in PowerShell is fragile. No error handling for claude CLI execution or JSON validation of output.\",\n      \"impact\": \"Script may fail silently or write invalid JSON to ai_review.json, breaking downstream consumers.\"\n    },\n    {\n      \"severity\": \"MEDIUM\",\n      \"location\": \"scripts/miyabi-finish.ps1:14-17\",\n      \"description\": \"Commented AI review code references bash script (pr_review.sh) instead of PowerShell version (pr_review.ps1).\",\n      \"impact\": \"Windows users cannot enable AI review functionality without code modification.\"\n    },\n    {\n      \"severity\": \"LOW\",\n      \"location\": \"scripts/miyabi-finish.ps1:23\",\n      \"description\": \"File missing newline at end. Can cause issues with git diffs and script concatenation.\",\n      \"impact\": \"Minor but violates best practices for text files.\"\n    }\n  ],\n  \"missing_checks\": [\n    {\n      \"item\": \"Parameter validation in miyabi-finish.ps1\",\n      \"details\": \"Issue parameter should be [Parameter(Mandatory=$true)] with pattern validation for numeric issue IDs.\"\n    },\n    {\n      \"item\": \"Git state validation before push\",\n      \"details\": \"Should check: working directory is clean, current branch is not main/master, origin remote exists.\"\n    },\n    {\n      \"item\": \"Error handling for git operations\",\n      \"details\": \"No $ErrorActionPreference setting or $LASTEXITCODE checks after git/gh commands in PowerShell scripts.\"\n    },\n    {\n      \"item\": \"JSON validation in pr_review.ps1\",\n      \"details\": \"Should validate claude output is valid JSON using Test-Json before writing to file.\"\n    },\n    {\n      \"item\": \"File existence checks\",\n      \"details\": \"miyabi-finish.ps1 should verify .github/pull_request_template.md exists before using --body-file.\"\n    },\n    {\n      \"item\": \"PowerShell version compatibility\",\n      \"details\": \"No minimum version specified. Scripts should document required PowerShell version (5.1 vs 7+).\"\n    },\n    {\n      \"item\": \"Testing coverage\",\n      \"details\": \"No unit tests, integration tests, or Pester tests provided for new PowerShell scripts.\"\n    },\n    {\n      \"item\": \"Windows usage documentation\",\n      \"details\": \"README.md lacks PowerShell usage examples and execution policy requirements for Windows users.\"\n    },\n    {\n      \"item\": \"Cross-platform script consistency\",\n      \"details\": \"No verification that PowerShell scripts behave identically to bash versions in equivalent scenarios.\"\n    }\n  ],\n  \"suggested_tasks\": [\n    {\n      \"priority\": \"CRITICAL\",\n      \"task\": \"Remove test line from README.md:52\",\n      \"rationale\": \"Production documentation should not contain test/debug content.\"\n    },\n    {\n      \"priority\": \"HIGH\",\n      \"task\": \"Add mandatory parameter validation to miyabi-finish.ps1\",\n      \"details\": \"Change to: [Parameter(Mandatory=$true)][ValidatePattern('^\\\\d+$')][string]$Issue\"\n    },\n    {\n      \"priority\": \"HIGH\",\n      \"task\": \"Add git push error handling in miyabi-finish.ps1\",\n      \"details\": \"Check $LASTEXITCODE after push, exit script if push fails before PR creation.\"\n    },\n    {\n      \"priority\": \"HIGH\",\n      \"task\": \"Add working directory validation before git push\",\n      \"details\": \"Check for uncommitted changes (git diff-index --quiet HEAD), verify not on main/master branch.\"\n    },\n    {\n      \"priority\": \"HIGH\",\n      \"task\": \"Fix commented AI review code to reference pr_review.ps1\",\n      \"details\": \"Line 15 should call PowerShell script, not bash: & .\\\\scripts\\\\ai\\\\pr_review.ps1\"\n    },\n    {\n      \"priority\": \"MEDIUM\",\n      \"task\": \"Add error handling to all PowerShell scripts\",\n      \"details\": \"Add $ErrorActionPreference = 'Stop' at script start or check $LASTEXITCODE after each external command.\"\n    },\n    {\n      \"priority\": \"MEDIUM\",\n      \"task\": \"Add JSON validation in pr_review.ps1\",\n      \"details\": \"Validate claude output with Test-Json, write error JSON if validation fails.\"\n    },\n    {\n      \"priority\": \"MEDIUM\",\n      \"task\": \"Add newline at end of miyabi-finish.ps1\",\n      \"details\": \"File should end with newline character per POSIX/git best practices.\"\n    },\n    {\n      \"priority\": \"MEDIUM\",\n      \"task\": \"Add file existence check for PR template\",\n      \"details\": \"Verify .github/pull_request_template.md exists before gh pr create in miyabi-finish.ps1.\"\n    },\n    {\n      \"priority\": \"LOW\",\n      \"task\": \"Create Pester test suite for PowerShell scripts\",\n      \"details\": \"Add tests for pr_review.ps1, miyabi-start.ps1, miyabi-finish.ps1 covering success and error scenarios.\"\n    },\n    {\n      \"priority\": \"LOW\",\n      \"task\": \"Add PowerShell usage examples to README.md\",\n      \"details\": \"Include Windows-specific instructions, execution policy notes, and PowerShell syntax examples.\"\n    },\n    {\n      \"priority\": \"LOW\",\n      \"task\": \"Document PowerShell version requirements\",\n      \"details\": \"Add #Requires -Version statement or comment specifying minimum PowerShell version.\"\n    },\n    {\n      \"priority\": \"LOW\",\n      \"task\": \"Add comment-based help to PowerShell scripts\",\n      \"details\": \"Include .SYNOPSIS, .DESCRIPTION, .PARAMETER, .EXAMPLE sections for Get-Help compatibility.\"\n    },\n    {\n      \"priority\": \"LOW\",\n      \"task\": \"Consider adding -WhatIf support for destructive operations\",\n      \"details\": \"miyabi-finish.ps1 should support [CmdletBinding(SupportsShouldProcess)] for git push preview.\"\n    }\n  ]\n}\n```\n\n**Key Findings:**\n\n1. **CRITICAL**: Test content in README.md (line 52) must be removed\n2. **HIGH**: Multiple error handling gaps in PowerShell scripts that could cause silent failures\n3. **HIGH**: Missing parameter validation allows scripts to run with invalid inputs\n4. **MEDIUM**: Incomplete Windows migration - commented code still references bash scripts\n5. **No tests** provided for any new PowerShell functionality\n\nThe review identified 7 risks, 9 missing checks, and 14 suggested tasks prioritized from CRITICAL to LOW.","session_id":"dc7c0ba1-c97c-4a23-94ef-556f5181615d","total_cost_usd":0.18556034999999999,"usage":{"input_tokens":19,"cache_creation_input_tokens":12092,"cache_read_input_tokens":82812,"output_tokens":5884,"server_tool_use":{"web_search_requests":0,"web_fetch_requests":0},"service_tier":"standard","cache_creation":{"ephemeral_1h_input_tokens":0,"ephemeral_5m_input_tokens":12092}},"modelUsage":{"claude-haiku-4-5-20251001":{"inputTokens":1822,"outputTokens":304,"cacheReadInputTokens":0,"cacheCreationInputTokens":0,"webSearchRequests":0,"costUSD":0.0033420000000000004,"contextWindow":200000},"claude-sonnet-4-5-20250929":{"inputTokens":22,"outputTokens":6977,"cacheReadInputTokens":82812,"cacheCreationInputTokens":14041,"webSearchRequests":0,"costUSD":0.18221834999999997,"contextWindow":200000}},"permission_denials":[{"tool_name":"Write","tool_use_id":"toolu_015QVfvjw6eGufd4bFrYzV4f","tool_input":{"file_path":"C:\\Users\\ThinkPad\\Desktop\\miyabi_consulting_os_kit\\ai_review.json","content":"{\n  \"summary\": \"Addition of PowerShell scripts for Windows support and minor documentation updates. The changes introduce platform-specific tooling but have several critical issues: missing error handling, test content in production docs, validation gaps, no tests, and incomplete PowerShell migration.\",\n  \"risks\": [\n    {\n      \"severity\": \"HIGH\",\n      \"location\": \"README.md:52\",\n      \"description\": \"Test/debug line added to production documentation: 'This is a test line for the dry run.' This should not be committed to main branch.\",\n      \"impact\": \"Unprofessional appearance, suggests incomplete testing or accidental commit.\"\n    },\n    {\n      \"severity\": \"HIGH\",\n      \"location\": \"scripts/miyabi-finish.ps1:11\",\n      \"description\": \"Unconditional git push without validation of working directory state, uncommitted changes, or push success. No error handling if push fails.\",\n      \"impact\": \"Could push broken/incomplete code, or continue to PR creation even if push fails, creating inconsistent state.\"\n    },\n    {\n      \"severity\": \"HIGH\",\n      \"location\": \"scripts/miyabi-finish.ps1:2-8\",\n      \"description\": \"Issue parameter is not mandatory and has no validation. User can execute script with empty/invalid issue number.\",\n      \"impact\": \"PR creation will fail or create PR with malformed title/references.\"\n    },\n    {\n      \"severity\": \"MEDIUM\",\n      \"location\": \"scripts/miyabi-finish.ps1:21\",\n      \"description\": \"PR creation uses --body-file but doesn't validate file exists or handle creation failures. No error checking after gh pr create.\",\n      \"impact\": \"Silent failures possible. User gets success message even if PR creation failed.\"\n    },\n    {\n      \"severity\": \"MEDIUM\",\n      \"location\": \"scripts/ai/pr_review.ps1:19-21\",\n      \"description\": \"Backtick line continuation in PowerShell is fragile. No error handling for claude CLI execution or JSON validation of output.\",\n      \"impact\": \"Script may fail silently or write invalid JSON to ai_review.json, breaking downstream consumers.\"\n    },\n    {\n      \"severity\": \"MEDIUM\",\n      \"location\": \"scripts/miyabi-finish.ps1:14-17\",\n      \"description\": \"Commented AI review code references bash script (pr_review.sh) instead of PowerShell version (pr_review.ps1).\",\n      \"impact\": \"Windows users cannot enable AI review functionality without code modification.\"\n    },\n    {\n      \"severity\": \"LOW\",\n      \"location\": \"scripts/miyabi-finish.ps1:23\",\n      \"description\": \"File missing newline at end. Can cause issues with git diffs and script concatenation.\",\n      \"impact\": \"Minor but violates best practices for text files.\"\n    }\n  ],\n  \"missing_checks\": [\n    {\n      \"item\": \"Parameter validation in miyabi-finish.ps1\",\n      \"details\": \"Issue parameter should be [Parameter(Mandatory=$true)] with pattern validation for numeric issue IDs.\"\n    },\n    {\n      \"item\": \"Git state validation before push\",\n      \"details\": \"Should check: working directory is clean, current branch is not main/master, origin remote exists.\"\n    },\n    {\n      \"item\": \"Error handling for git operations\",\n      \"details\": \"No $ErrorActionPreference setting or $LASTEXITCODE checks after git/gh commands in PowerShell scripts.\"\n    },\n    {\n      \"item\": \"JSON validation in pr_review.ps1\",\n      \"details\": \"Should validate claude output is valid JSON using Test-Json before writing to file.\"\n    },\n    {\n      \"item\": \"File existence checks\",\n      \"details\": \"miyabi-finish.ps1 should verify .github/pull_request_template.md exists before using --body-file.\"\n    },\n    {\n      \"item\": \"PowerShell version compatibility\",\n      \"details\": \"No minimum version specified. Scripts should document required PowerShell version (5.1 vs 7+).\"\n    },\n    {\n      \"item\": \"Testing coverage\",\n      \"details\": \"No unit tests, integration tests, or Pester tests provided for new PowerShell scripts.\"\n    },\n    {\n      \"item\": \"Windows usage documentation\",\n      \"details\": \"README.md lacks PowerShell usage examples and execution policy requirements for Windows users.\"\n    },\n    {\n      \"item\": \"Cross-platform script consistency\",\n      \"details\": \"No verification that PowerShell scripts behave identically to bash versions in equivalent scenarios.\"\n    }\n  ],\n  \"suggested_tasks\": [\n    {\n      \"priority\": \"CRITICAL\",\n      \"task\": \"Remove test line from README.md:52\",\n      \"rationale\": \"Production documentation should not contain test/debug content.\"\n    },\n    {\n      \"priority\": \"HIGH\",\n      \"task\": \"Add mandatory parameter validation to miyabi-finish.ps1\",\n      \"details\": \"Change to: [Parameter(Mandatory=$true)][ValidatePattern('^\\\\d+$')][string]$Issue\"\n    },\n    {\n      \"priority\": \"HIGH\",\n      \"task\": \"Add git push error handling in miyabi-finish.ps1\",\n      \"details\": \"Check $LASTEXITCODE after push, exit script if push fails before PR creation.\"\n    },\n    {\n      \"priority\": \"HIGH\",\n      \"task\": \"Add working directory validation before git push\",\n      \"details\": \"Check for uncommitted changes (git diff-index --quiet HEAD), verify not on main/master branch.\"\n    },\n    {\n      \"priority\": \"HIGH\",\n      \"task\": \"Fix commented AI review code to reference pr_review.ps1\",\n      \"details\": \"Line 15 should call PowerShell script, not bash: & .\\\\scripts\\\\ai\\\\pr_review.ps1\"\n    },\n    {\n      \"priority\": \"MEDIUM\",\n      \"task\": \"Add error handling to all PowerShell scripts\",\n      \"details\": \"Add $ErrorActionPreference = 'Stop' at script start or check $LASTEXITCODE after each external command.\"\n    },\n    {\n      \"priority\": \"MEDIUM\",\n      \"task\": \"Add JSON validation in pr_review.ps1\",\n      \"details\": \"Validate claude output with Test-Json, write error JSON if validation fails.\"\n    },\n    {\n      \"priority\": \"MEDIUM\",\n      \"task\": \"Add newline at end of miyabi-finish.ps1\",\n      \"details\": \"File should end with newline character per POSIX/git best practices.\"\n    },\n    {\n      \"priority\": \"MEDIUM\",\n      \"task\": \"Add file existence check for PR template\",\n      \"details\": \"Verify .github/pull_request_template.md exists before gh pr create in miyabi-finish.ps1.\"\n    },\n    {\n      \"priority\": \"LOW\",\n      \"task\": \"Create Pester test suite for PowerShell scripts\",\n      \"details\": \"Add tests for pr_review.ps1, miyabi-start.ps1, miyabi-finish.ps1 covering success and error scenarios.\"\n    },\n    {\n      \"priority\": \"LOW\",\n      \"task\": \"Add PowerShell usage examples to README.md\",\n      \"details\": \"Include Windows-specific instructions, execution policy notes, and PowerShell syntax examples.\"\n    },\n    {\n      \"priority\": \"LOW\",\n      \"task\": \"Document PowerShell version requirements\",\n      \"details\": \"Add #Requires -Version statement or comment specifying minimum PowerShell version.\"\n    },\n    {\n      \"priority\": \"LOW\",\n      \"task\": \"Add comment-based help to PowerShell scripts\",\n      \"details\": \"Include .SYNOPSIS, .DESCRIPTION, .PARAMETER, .EXAMPLE sections for Get-Help compatibility.\"\n    },\n    {\n      \"priority\": \"LOW\",\n      \"task\": \"Consider adding -WhatIf support for destructive operations\",\n      \"details\": \"miyabi-finish.ps1 should support [CmdletBinding(SupportsShouldProcess)] for git push preview.\"\n    }\n  ]\n}\n"}}],"uuid":"530bda0c-c7c4-4677-9be9-5fa551cc0bd8"}
